lexandra/__init__.py
lexandra/utils.py
lexandra/core/__init__.py
lexandra/core/cursor.py
lexandra/core/lexer.py
lexandra/core/token.py
lexandra/factory/__init__.py
lexandra/factory/constants.py
lexandra/factory/lexers.py
lexandra-1.0.0.dist-info/LICENSE
lexandra-1.0.0.dist-info/METADATA
lexandra-1.0.0.dist-info/WHEEL
lexandra-1.0.0.dist-info/top_level.txt
lexandra-1.0.0.dist-info/RECORD
