Metadata-Version: 2.1
Name: lexandra
Version: 1.0.0
Summary: Create a lexer by decorators.
Author-email: Del Pino Agustín <dpinoagustin@gmail.com>
Project-URL: Homepage, https://github.com/agustin-del-pino/lexandra
Project-URL: Bug Tracker, https://github.com/agustin-del-pino/lexandra/issues
Classifier: Programming Language :: Python :: 3
Classifier: License :: OSI Approved :: MIT License
Classifier: Operating System :: OS Independent
Requires-Python: >=3.7
License-File: LICENSE
